{
    "61501287d8da0cd5": [
        {
            "ts": 1782115476,
            "status": "UP",
            "latency_ms": 1
        },
        {
            "ts": 1782115481,
            "status": "UP",
            "latency_ms": 1
        },
        {
            "ts": 1782115486,
            "status": "UP",
            "latency_ms": 1
        },
        {
            "ts": 1782115491,
            "status": "UP",
            "latency_ms": 1
        },
        {
            "ts": 1782115496,
            "status": "UP",
            "latency_ms": 1
        },
        {
            "ts": 1782115501,
            "status": "UP",
            "latency_ms": 1
        },
        {
            "ts": 1782115506,
            "status": "UP",
            "latency_ms": 1
        },
        {
            "ts": 1782115511,
            "status": "UP",
            "latency_ms": 1
        },
        {
            "ts": 1782115516,
            "status": "UP",
            "latency_ms": 1
        },
        {
            "ts": 1782115521,
            "status": "UP",
            "latency_ms": 2
        },
        {
            "ts": 1782115526,
            "status": "UP",
            "latency_ms": 2
        },
        {
            "ts": 1782115531,
            "status": "UP",
            "latency_ms": 1
        },
        {
            "ts": 1782115536,
            "status": "UP",
            "latency_ms": 1
        },
        {
            "ts": 1782115551,
            "status": "UP",
            "latency_ms": 1
        },
        {
            "ts": 1782115556,
            "status": "UP",
            "latency_ms": 1
        },
        {
            "ts": 1782115561,
            "status": "UP",
            "latency_ms": 1
        },
        {
            "ts": 1782115566,
            "status": "UP",
            "latency_ms": 1
        },
        {
            "ts": 1782115572,
            "status": "UP",
            "latency_ms": 1
        },
        {
            "ts": 1782115576,
            "status": "UP",
            "latency_ms": 1
        },
        {
            "ts": 1782115581,
            "status": "UP",
            "latency_ms": 1
        },
        {
            "ts": 1782115582,
            "status": "UP",
            "latency_ms": 1
        },
        {
            "ts": 1782115587,
            "status": "UP",
            "latency_ms": 1
        },
        {
            "ts": 1782115592,
            "status": "UP",
            "latency_ms": 1
        },
        {
            "ts": 1782115597,
            "status": "UP",
            "latency_ms": 1
        },
        {
            "ts": 1782115602,
            "status": "UP",
            "latency_ms": 1
        },
        {
            "ts": 1782115607,
            "status": "UP",
            "latency_ms": 1
        },
        {
            "ts": 1782115612,
            "status": "UP",
            "latency_ms": 2
        },
        {
            "ts": 1782115618,
            "status": "UP",
            "latency_ms": 1
        },
        {
            "ts": 1782115622,
            "status": "UP",
            "latency_ms": 1
        },
        {
            "ts": 1782115627,
            "status": "UP",
            "latency_ms": 1
        },
        {
            "ts": 1782115632,
            "status": "UP",
            "latency_ms": 1
        },
        {
            "ts": 1782115637,
            "status": "UP",
            "latency_ms": 1
        },
        {
            "ts": 1782115642,
            "status": "UP",
            "latency_ms": 1
        },
        {
            "ts": 1782115647,
            "status": "UP",
            "latency_ms": 1
        },
        {
            "ts": 1782115691,
            "status": "UP",
            "latency_ms": 1
        },
        {
            "ts": 1782115700,
            "status": "UP",
            "latency_ms": 1
        },
        {
            "ts": 1782115702,
            "status": "UP",
            "latency_ms": 2
        },
        {
            "ts": 1782115704,
            "status": "UP",
            "latency_ms": 2
        },
        {
            "ts": 1782115709,
            "status": "UP",
            "latency_ms": 1
        },
        {
            "ts": 1782115714,
            "status": "UP",
            "latency_ms": 1
        },
        {
            "ts": 1782115719,
            "status": "UP",
            "latency_ms": 1
        },
        {
            "ts": 1782115724,
            "status": "UP",
            "latency_ms": 1
        },
        {
            "ts": 1782115729,
            "status": "UP",
            "latency_ms": 2
        },
        {
            "ts": 1782115734,
            "status": "UP",
            "latency_ms": 1
        },
        {
            "ts": 1782115739,
            "status": "UP",
            "latency_ms": 8
        },
        {
            "ts": 1782115740,
            "status": "UP",
            "latency_ms": 2
        },
        {
            "ts": 1782115756,
            "status": "UP",
            "latency_ms": 2
        },
        {
            "ts": 1782115759,
            "status": "UP",
            "latency_ms": 2
        },
        {
            "ts": 1782115764,
            "status": "UP",
            "latency_ms": 2
        },
        {
            "ts": 1782115769,
            "status": "UP",
            "latency_ms": 1
        },
        {
            "ts": 1782115774,
            "status": "UP",
            "latency_ms": 1
        },
        {
            "ts": 1782115777,
            "status": "UP",
            "latency_ms": 1
        },
        {
            "ts": 1782115782,
            "status": "UP",
            "latency_ms": 1
        },
        {
            "ts": 1782115787,
            "status": "UP",
            "latency_ms": 1
        },
        {
            "ts": 1782115792,
            "status": "UP",
            "latency_ms": 1
        },
        {
            "ts": 1782115797,
            "status": "UP",
            "latency_ms": 1
        },
        {
            "ts": 1782115802,
            "status": "UP",
            "latency_ms": 1
        },
        {
            "ts": 1782115807,
            "status": "UP",
            "latency_ms": 1
        },
        {
            "ts": 1782115812,
            "status": "UP",
            "latency_ms": 1
        },
        {
            "ts": 1782115817,
            "status": "UP",
            "latency_ms": 1
        }
    ],
    "385192c874026067": [
        {
            "ts": 1783554683,
            "status": "UP",
            "latency_ms": 0.5,
            "packet_loss_pct": 0
        },
        {
            "ts": 1783554742,
            "status": "UP",
            "latency_ms": 0.6,
            "packet_loss_pct": 0
        },
        {
            "ts": 1783554802,
            "status": "UP",
            "latency_ms": 0.5,
            "packet_loss_pct": 0
        },
        {
            "ts": 1783554862,
            "status": "UP",
            "latency_ms": 0.5,
            "packet_loss_pct": 0
        },
        {
            "ts": 1783554922,
            "status": "UP",
            "latency_ms": 0.5,
            "packet_loss_pct": 0
        },
        {
            "ts": 1783554982,
            "status": "UP",
            "latency_ms": 0.5,
            "packet_loss_pct": 0
        },
        {
            "ts": 1783555042,
            "status": "UP",
            "latency_ms": 1.4,
            "packet_loss_pct": 0
        },
        {
            "ts": 1783555102,
            "status": "UP",
            "latency_ms": 0.5,
            "packet_loss_pct": 0
        },
        {
            "ts": 1783555162,
            "status": "UP",
            "latency_ms": 0.5,
            "packet_loss_pct": 0
        },
        {
            "ts": 1783555222,
            "status": "UP",
            "latency_ms": 0.5,
            "packet_loss_pct": 0
        },
        {
            "ts": 1783555282,
            "status": "UP",
            "latency_ms": 0.5,
            "packet_loss_pct": 0
        },
        {
            "ts": 1783555342,
            "status": "UP",
            "latency_ms": 0.5,
            "packet_loss_pct": 0
        },
        {
            "ts": 1783555402,
            "status": "UP",
            "latency_ms": 0.5,
            "packet_loss_pct": 0
        },
        {
            "ts": 1783555462,
            "status": "UP",
            "latency_ms": 0.5,
            "packet_loss_pct": 0
        },
        {
            "ts": 1783555522,
            "status": "UP",
            "latency_ms": 0.5,
            "packet_loss_pct": 0
        },
        {
            "ts": 1783555582,
            "status": "UP",
            "latency_ms": 0.5,
            "packet_loss_pct": 0
        },
        {
            "ts": 1783555642,
            "status": "UP",
            "latency_ms": 0.5,
            "packet_loss_pct": 0
        },
        {
            "ts": 1783555702,
            "status": "UP",
            "latency_ms": 0.5,
            "packet_loss_pct": 0
        },
        {
            "ts": 1783555762,
            "status": "UP",
            "latency_ms": 0.5,
            "packet_loss_pct": 0
        },
        {
            "ts": 1783555822,
            "status": "UP",
            "latency_ms": 0.5,
            "packet_loss_pct": 0
        },
        {
            "ts": 1783555882,
            "status": "UP",
            "latency_ms": 0.5,
            "packet_loss_pct": 0
        },
        {
            "ts": 1783555942,
            "status": "UP",
            "latency_ms": 0.5,
            "packet_loss_pct": 0
        },
        {
            "ts": 1783556010,
            "status": "UP",
            "latency_ms": 0.5,
            "packet_loss_pct": 0
        },
        {
            "ts": 1783556062,
            "status": "UP",
            "latency_ms": 0.5,
            "packet_loss_pct": 0
        },
        {
            "ts": 1783556122,
            "status": "UP",
            "latency_ms": 0.5,
            "packet_loss_pct": 0
        },
        {
            "ts": 1783556182,
            "status": "UP",
            "latency_ms": 0.5,
            "packet_loss_pct": 0
        },
        {
            "ts": 1783556242,
            "status": "UP",
            "latency_ms": 0.5,
            "packet_loss_pct": 0
        },
        {
            "ts": 1783556302,
            "status": "UP",
            "latency_ms": 0.5,
            "packet_loss_pct": 0
        },
        {
            "ts": 1783556362,
            "status": "UP",
            "latency_ms": 0.5,
            "packet_loss_pct": 0
        },
        {
            "ts": 1783556422,
            "status": "UP",
            "latency_ms": 0.6,
            "packet_loss_pct": 0
        },
        {
            "ts": 1783556482,
            "status": "UP",
            "latency_ms": 0.5,
            "packet_loss_pct": 0
        },
        {
            "ts": 1783556542,
            "status": "UP",
            "latency_ms": 0.5,
            "packet_loss_pct": 0
        },
        {
            "ts": 1783556602,
            "status": "UP",
            "latency_ms": 0.5,
            "packet_loss_pct": 0
        },
        {
            "ts": 1783556662,
            "status": "UP",
            "latency_ms": 0.5,
            "packet_loss_pct": 0
        },
        {
            "ts": 1783556722,
            "status": "UP",
            "latency_ms": 0.5,
            "packet_loss_pct": 0
        },
        {
            "ts": 1783556782,
            "status": "UP",
            "latency_ms": 0.5,
            "packet_loss_pct": 0
        },
        {
            "ts": 1783556842,
            "status": "UP",
            "latency_ms": 0.5,
            "packet_loss_pct": 0
        },
        {
            "ts": 1783556902,
            "status": "UP",
            "latency_ms": 0.5,
            "packet_loss_pct": 0
        },
        {
            "ts": 1783556962,
            "status": "UP",
            "latency_ms": 0.5,
            "packet_loss_pct": 0
        },
        {
            "ts": 1783557022,
            "status": "UP",
            "latency_ms": 0.5,
            "packet_loss_pct": 0
        },
        {
            "ts": 1783557082,
            "status": "UP",
            "latency_ms": 0.5,
            "packet_loss_pct": 0
        },
        {
            "ts": 1783557142,
            "status": "UP",
            "latency_ms": 0.5,
            "packet_loss_pct": 0
        },
        {
            "ts": 1783557202,
            "status": "UP",
            "latency_ms": 0.5,
            "packet_loss_pct": 0
        },
        {
            "ts": 1783557262,
            "status": "UP",
            "latency_ms": 0.5,
            "packet_loss_pct": 0
        },
        {
            "ts": 1783557322,
            "status": "UP",
            "latency_ms": 0.5,
            "packet_loss_pct": 0
        },
        {
            "ts": 1783557382,
            "status": "UP",
            "latency_ms": 0.5,
            "packet_loss_pct": 0
        },
        {
            "ts": 1783557450,
            "status": "UP",
            "latency_ms": 0.5,
            "packet_loss_pct": 0
        },
        {
            "ts": 1783557502,
            "status": "UP",
            "latency_ms": 0.5,
            "packet_loss_pct": 0
        },
        {
            "ts": 1783557562,
            "status": "UP",
            "latency_ms": 0.5,
            "packet_loss_pct": 0
        },
        {
            "ts": 1783557622,
            "status": "UP",
            "latency_ms": 0.5,
            "packet_loss_pct": 0
        },
        {
            "ts": 1783557682,
            "status": "UP",
            "latency_ms": 0.5,
            "packet_loss_pct": 0
        },
        {
            "ts": 1783557742,
            "status": "UP",
            "latency_ms": 0.5,
            "packet_loss_pct": 0
        },
        {
            "ts": 1783557802,
            "status": "UP",
            "latency_ms": 0.5,
            "packet_loss_pct": 0
        },
        {
            "ts": 1783557862,
            "status": "UP",
            "latency_ms": 0.5,
            "packet_loss_pct": 0
        },
        {
            "ts": 1783557922,
            "status": "UP",
            "latency_ms": 0.5,
            "packet_loss_pct": 0
        },
        {
            "ts": 1783557982,
            "status": "UP",
            "latency_ms": 0.5,
            "packet_loss_pct": 0
        },
        {
            "ts": 1783558042,
            "status": "UP",
            "latency_ms": 0.5,
            "packet_loss_pct": 0
        },
        {
            "ts": 1783558103,
            "status": "UP",
            "latency_ms": 0.5,
            "packet_loss_pct": 0
        },
        {
            "ts": 1783560774,
            "status": "UP",
            "latency_ms": 0.5,
            "packet_loss_pct": 0
        },
        {
            "ts": 1783560788,
            "status": "UP",
            "latency_ms": 0.5,
            "packet_loss_pct": 0
        }
    ],
    "70a4af7fba5c9929": [
        {
            "ts": 1783554683,
            "status": "UP",
            "latency_ms": 0.5,
            "packet_loss_pct": 0
        },
        {
            "ts": 1783554742,
            "status": "UP",
            "latency_ms": 0.5,
            "packet_loss_pct": 0
        },
        {
            "ts": 1783554802,
            "status": "UP",
            "latency_ms": 0.5,
            "packet_loss_pct": 0
        },
        {
            "ts": 1783554862,
            "status": "UP",
            "latency_ms": 0.5,
            "packet_loss_pct": 0
        },
        {
            "ts": 1783554922,
            "status": "UP",
            "latency_ms": 0.5,
            "packet_loss_pct": 0
        },
        {
            "ts": 1783554982,
            "status": "UP",
            "latency_ms": 0.5,
            "packet_loss_pct": 0
        },
        {
            "ts": 1783555042,
            "status": "UP",
            "latency_ms": 0.5,
            "packet_loss_pct": 0
        },
        {
            "ts": 1783555102,
            "status": "UP",
            "latency_ms": 0.5,
            "packet_loss_pct": 0
        },
        {
            "ts": 1783555162,
            "status": "UP",
            "latency_ms": 0.5,
            "packet_loss_pct": 0
        },
        {
            "ts": 1783555222,
            "status": "UP",
            "latency_ms": 0.5,
            "packet_loss_pct": 0
        },
        {
            "ts": 1783555282,
            "status": "UP",
            "latency_ms": 0.5,
            "packet_loss_pct": 0
        },
        {
            "ts": 1783555342,
            "status": "UP",
            "latency_ms": 0.5,
            "packet_loss_pct": 0
        },
        {
            "ts": 1783555402,
            "status": "UP",
            "latency_ms": 0.5,
            "packet_loss_pct": 0
        },
        {
            "ts": 1783555462,
            "status": "UP",
            "latency_ms": 0.5,
            "packet_loss_pct": 0
        },
        {
            "ts": 1783555522,
            "status": "UP",
            "latency_ms": 0.5,
            "packet_loss_pct": 0
        },
        {
            "ts": 1783555582,
            "status": "UP",
            "latency_ms": 0.5,
            "packet_loss_pct": 0
        },
        {
            "ts": 1783555642,
            "status": "UP",
            "latency_ms": 0.5,
            "packet_loss_pct": 0
        },
        {
            "ts": 1783555702,
            "status": "UP",
            "latency_ms": 0.5,
            "packet_loss_pct": 0
        },
        {
            "ts": 1783555762,
            "status": "UP",
            "latency_ms": 0.5,
            "packet_loss_pct": 0
        },
        {
            "ts": 1783555822,
            "status": "UP",
            "latency_ms": 0.5,
            "packet_loss_pct": 0
        },
        {
            "ts": 1783555882,
            "status": "UP",
            "latency_ms": 0.5,
            "packet_loss_pct": 0
        },
        {
            "ts": 1783555942,
            "status": "UP",
            "latency_ms": 0.5,
            "packet_loss_pct": 0
        },
        {
            "ts": 1783556010,
            "status": "UP",
            "latency_ms": 0.5,
            "packet_loss_pct": 0
        },
        {
            "ts": 1783556062,
            "status": "UP",
            "latency_ms": 0.5,
            "packet_loss_pct": 0
        },
        {
            "ts": 1783556122,
            "status": "UP",
            "latency_ms": 0.5,
            "packet_loss_pct": 0
        },
        {
            "ts": 1783556182,
            "status": "UP",
            "latency_ms": 0.5,
            "packet_loss_pct": 0
        },
        {
            "ts": 1783556242,
            "status": "UP",
            "latency_ms": 0.5,
            "packet_loss_pct": 0
        },
        {
            "ts": 1783556302,
            "status": "UP",
            "latency_ms": 0.5,
            "packet_loss_pct": 0
        },
        {
            "ts": 1783556362,
            "status": "UP",
            "latency_ms": 0.5,
            "packet_loss_pct": 0
        },
        {
            "ts": 1783556422,
            "status": "UP",
            "latency_ms": 0.5,
            "packet_loss_pct": 0
        },
        {
            "ts": 1783556482,
            "status": "UP",
            "latency_ms": 0.5,
            "packet_loss_pct": 0
        },
        {
            "ts": 1783556542,
            "status": "UP",
            "latency_ms": 0.5,
            "packet_loss_pct": 0
        },
        {
            "ts": 1783556602,
            "status": "UP",
            "latency_ms": 0.5,
            "packet_loss_pct": 0
        },
        {
            "ts": 1783556662,
            "status": "UP",
            "latency_ms": 0.5,
            "packet_loss_pct": 0
        },
        {
            "ts": 1783556722,
            "status": "UP",
            "latency_ms": 0.5,
            "packet_loss_pct": 0
        },
        {
            "ts": 1783556782,
            "status": "UP",
            "latency_ms": 0.5,
            "packet_loss_pct": 0
        },
        {
            "ts": 1783556842,
            "status": "UP",
            "latency_ms": 0.5,
            "packet_loss_pct": 0
        },
        {
            "ts": 1783556902,
            "status": "UP",
            "latency_ms": 0.5,
            "packet_loss_pct": 0
        },
        {
            "ts": 1783556962,
            "status": "UP",
            "latency_ms": 0.5,
            "packet_loss_pct": 0
        },
        {
            "ts": 1783557022,
            "status": "UP",
            "latency_ms": 0.5,
            "packet_loss_pct": 0
        },
        {
            "ts": 1783557082,
            "status": "UP",
            "latency_ms": 0.5,
            "packet_loss_pct": 0
        },
        {
            "ts": 1783557142,
            "status": "UP",
            "latency_ms": 0.5,
            "packet_loss_pct": 0
        },
        {
            "ts": 1783557202,
            "status": "UP",
            "latency_ms": 0.5,
            "packet_loss_pct": 0
        },
        {
            "ts": 1783557262,
            "status": "UP",
            "latency_ms": 0.5,
            "packet_loss_pct": 0
        },
        {
            "ts": 1783557322,
            "status": "UP",
            "latency_ms": 0.5,
            "packet_loss_pct": 0
        },
        {
            "ts": 1783557382,
            "status": "UP",
            "latency_ms": 0.5,
            "packet_loss_pct": 0
        },
        {
            "ts": 1783557450,
            "status": "UP",
            "latency_ms": 0.5,
            "packet_loss_pct": 0
        },
        {
            "ts": 1783557502,
            "status": "UP",
            "latency_ms": 0.5,
            "packet_loss_pct": 0
        },
        {
            "ts": 1783557562,
            "status": "UP",
            "latency_ms": 0.5,
            "packet_loss_pct": 0
        },
        {
            "ts": 1783557622,
            "status": "UP",
            "latency_ms": 0.5,
            "packet_loss_pct": 0
        },
        {
            "ts": 1783557682,
            "status": "UP",
            "latency_ms": 0.5,
            "packet_loss_pct": 0
        },
        {
            "ts": 1783557742,
            "status": "UP",
            "latency_ms": 0.5,
            "packet_loss_pct": 0
        },
        {
            "ts": 1783557802,
            "status": "UP",
            "latency_ms": 0.5,
            "packet_loss_pct": 0
        },
        {
            "ts": 1783557862,
            "status": "UP",
            "latency_ms": 0.5,
            "packet_loss_pct": 0
        },
        {
            "ts": 1783557922,
            "status": "UP",
            "latency_ms": 0.5,
            "packet_loss_pct": 0
        },
        {
            "ts": 1783557982,
            "status": "UP",
            "latency_ms": 0.5,
            "packet_loss_pct": 0
        },
        {
            "ts": 1783558042,
            "status": "UP",
            "latency_ms": 0.5,
            "packet_loss_pct": 0
        },
        {
            "ts": 1783558103,
            "status": "UP",
            "latency_ms": 0.5,
            "packet_loss_pct": 0
        },
        {
            "ts": 1783560774,
            "status": "UP",
            "latency_ms": 0.5,
            "packet_loss_pct": 0
        },
        {
            "ts": 1783560788,
            "status": "UP",
            "latency_ms": 0.5,
            "packet_loss_pct": 0
        }
    ],
    "250cc01c588e0e02": [
        {
            "ts": 1783554683,
            "status": "UP",
            "latency_ms": 0.5,
            "packet_loss_pct": 0
        },
        {
            "ts": 1783554742,
            "status": "UP",
            "latency_ms": 0.5,
            "packet_loss_pct": 0
        },
        {
            "ts": 1783554802,
            "status": "UP",
            "latency_ms": 0.5,
            "packet_loss_pct": 0
        },
        {
            "ts": 1783554862,
            "status": "UP",
            "latency_ms": 0.5,
            "packet_loss_pct": 0
        },
        {
            "ts": 1783554922,
            "status": "UP",
            "latency_ms": 0.5,
            "packet_loss_pct": 0
        },
        {
            "ts": 1783554982,
            "status": "UP",
            "latency_ms": 0.5,
            "packet_loss_pct": 0
        },
        {
            "ts": 1783555042,
            "status": "UP",
            "latency_ms": 0.5,
            "packet_loss_pct": 0
        },
        {
            "ts": 1783555102,
            "status": "UP",
            "latency_ms": 0.5,
            "packet_loss_pct": 0
        },
        {
            "ts": 1783555162,
            "status": "UP",
            "latency_ms": 0.5,
            "packet_loss_pct": 0
        },
        {
            "ts": 1783555222,
            "status": "UP",
            "latency_ms": 0.5,
            "packet_loss_pct": 0
        },
        {
            "ts": 1783555282,
            "status": "UP",
            "latency_ms": 0.5,
            "packet_loss_pct": 0
        },
        {
            "ts": 1783555342,
            "status": "UP",
            "latency_ms": 0.5,
            "packet_loss_pct": 0
        },
        {
            "ts": 1783555402,
            "status": "UP",
            "latency_ms": 0.5,
            "packet_loss_pct": 0
        },
        {
            "ts": 1783555462,
            "status": "UP",
            "latency_ms": 0.5,
            "packet_loss_pct": 0
        },
        {
            "ts": 1783555522,
            "status": "UP",
            "latency_ms": 0.5,
            "packet_loss_pct": 0
        },
        {
            "ts": 1783555582,
            "status": "UP",
            "latency_ms": 0.5,
            "packet_loss_pct": 0
        },
        {
            "ts": 1783555642,
            "status": "UP",
            "latency_ms": 0.5,
            "packet_loss_pct": 0
        },
        {
            "ts": 1783555702,
            "status": "UP",
            "latency_ms": 0.5,
            "packet_loss_pct": 0
        },
        {
            "ts": 1783555762,
            "status": "UP",
            "latency_ms": 0.5,
            "packet_loss_pct": 0
        },
        {
            "ts": 1783555822,
            "status": "UP",
            "latency_ms": 0.5,
            "packet_loss_pct": 0
        },
        {
            "ts": 1783555882,
            "status": "UP",
            "latency_ms": 0.5,
            "packet_loss_pct": 0
        },
        {
            "ts": 1783555942,
            "status": "UP",
            "latency_ms": 0.5,
            "packet_loss_pct": 0
        },
        {
            "ts": 1783556010,
            "status": "UP",
            "latency_ms": 0.5,
            "packet_loss_pct": 0
        },
        {
            "ts": 1783556062,
            "status": "UP",
            "latency_ms": 0.5,
            "packet_loss_pct": 0
        },
        {
            "ts": 1783556122,
            "status": "UP",
            "latency_ms": 0.5,
            "packet_loss_pct": 0
        },
        {
            "ts": 1783556182,
            "status": "UP",
            "latency_ms": 0.5,
            "packet_loss_pct": 0
        },
        {
            "ts": 1783556242,
            "status": "UP",
            "latency_ms": 0.5,
            "packet_loss_pct": 0
        },
        {
            "ts": 1783556302,
            "status": "UP",
            "latency_ms": 0.5,
            "packet_loss_pct": 0
        },
        {
            "ts": 1783556362,
            "status": "UP",
            "latency_ms": 0.5,
            "packet_loss_pct": 0
        },
        {
            "ts": 1783556422,
            "status": "UP",
            "latency_ms": 0.5,
            "packet_loss_pct": 0
        },
        {
            "ts": 1783556482,
            "status": "UP",
            "latency_ms": 0.5,
            "packet_loss_pct": 0
        },
        {
            "ts": 1783556542,
            "status": "UP",
            "latency_ms": 0.5,
            "packet_loss_pct": 0
        },
        {
            "ts": 1783556602,
            "status": "UP",
            "latency_ms": 0.5,
            "packet_loss_pct": 0
        },
        {
            "ts": 1783556662,
            "status": "UP",
            "latency_ms": 0.5,
            "packet_loss_pct": 0
        },
        {
            "ts": 1783556722,
            "status": "UP",
            "latency_ms": 0.5,
            "packet_loss_pct": 0
        },
        {
            "ts": 1783556782,
            "status": "UP",
            "latency_ms": 0.5,
            "packet_loss_pct": 0
        },
        {
            "ts": 1783556842,
            "status": "UP",
            "latency_ms": 0.5,
            "packet_loss_pct": 0
        },
        {
            "ts": 1783556902,
            "status": "UP",
            "latency_ms": 0.5,
            "packet_loss_pct": 0
        },
        {
            "ts": 1783556962,
            "status": "UP",
            "latency_ms": 0.5,
            "packet_loss_pct": 0
        },
        {
            "ts": 1783557022,
            "status": "UP",
            "latency_ms": 0.5,
            "packet_loss_pct": 0
        },
        {
            "ts": 1783557082,
            "status": "UP",
            "latency_ms": 0.5,
            "packet_loss_pct": 0
        },
        {
            "ts": 1783557142,
            "status": "UP",
            "latency_ms": 0.5,
            "packet_loss_pct": 0
        },
        {
            "ts": 1783557202,
            "status": "UP",
            "latency_ms": 0.5,
            "packet_loss_pct": 0
        },
        {
            "ts": 1783557262,
            "status": "UP",
            "latency_ms": 0.5,
            "packet_loss_pct": 0
        },
        {
            "ts": 1783557322,
            "status": "UP",
            "latency_ms": 0.5,
            "packet_loss_pct": 0
        },
        {
            "ts": 1783557382,
            "status": "UP",
            "latency_ms": 0.5,
            "packet_loss_pct": 0
        },
        {
            "ts": 1783557450,
            "status": "UP",
            "latency_ms": 0.5,
            "packet_loss_pct": 0
        },
        {
            "ts": 1783557502,
            "status": "UP",
            "latency_ms": 0.5,
            "packet_loss_pct": 0
        },
        {
            "ts": 1783557562,
            "status": "UP",
            "latency_ms": 0.5,
            "packet_loss_pct": 0
        },
        {
            "ts": 1783557622,
            "status": "UP",
            "latency_ms": 0.5,
            "packet_loss_pct": 0
        },
        {
            "ts": 1783557682,
            "status": "UP",
            "latency_ms": 0.5,
            "packet_loss_pct": 0
        },
        {
            "ts": 1783557742,
            "status": "UP",
            "latency_ms": 0.5,
            "packet_loss_pct": 0
        },
        {
            "ts": 1783557802,
            "status": "UP",
            "latency_ms": 0.5,
            "packet_loss_pct": 0
        },
        {
            "ts": 1783557862,
            "status": "UP",
            "latency_ms": 0.5,
            "packet_loss_pct": 0
        },
        {
            "ts": 1783557922,
            "status": "UP",
            "latency_ms": 0.5,
            "packet_loss_pct": 0
        },
        {
            "ts": 1783557982,
            "status": "UP",
            "latency_ms": 0.5,
            "packet_loss_pct": 0
        },
        {
            "ts": 1783558042,
            "status": "UP",
            "latency_ms": 0.5,
            "packet_loss_pct": 0
        },
        {
            "ts": 1783558103,
            "status": "UP",
            "latency_ms": 0.5,
            "packet_loss_pct": 0
        },
        {
            "ts": 1783560774,
            "status": "UP",
            "latency_ms": 0.5,
            "packet_loss_pct": 0
        },
        {
            "ts": 1783560788,
            "status": "UP",
            "latency_ms": 0.5,
            "packet_loss_pct": 0
        }
    ],
    "ef1945006a4d6f45": [
        {
            "ts": 1782217379,
            "status": "UP",
            "latency_ms": 0.5,
            "packet_loss_pct": 0
        },
        {
            "ts": 1782217395,
            "status": "UP",
            "latency_ms": 0.5,
            "packet_loss_pct": 0
        },
        {
            "ts": 1782217409,
            "status": "UP",
            "latency_ms": 0.5,
            "packet_loss_pct": 0
        },
        {
            "ts": 1782217424,
            "status": "UP",
            "latency_ms": 0.5,
            "packet_loss_pct": 0
        },
        {
            "ts": 1782217439,
            "status": "UP",
            "latency_ms": 0.5,
            "packet_loss_pct": 0
        },
        {
            "ts": 1782217455,
            "status": "UP",
            "latency_ms": 0.5,
            "packet_loss_pct": 0
        },
        {
            "ts": 1782217468,
            "status": "UP",
            "latency_ms": 0.5,
            "packet_loss_pct": 0
        },
        {
            "ts": 1782217484,
            "status": "UP",
            "latency_ms": 0.5,
            "packet_loss_pct": 0
        },
        {
            "ts": 1782217498,
            "status": "UP",
            "latency_ms": 0.5,
            "packet_loss_pct": 0
        },
        {
            "ts": 1782217504,
            "status": "UP",
            "latency_ms": 0.5,
            "packet_loss_pct": 0
        },
        {
            "ts": 1782217515,
            "status": "UP",
            "latency_ms": 0.5,
            "packet_loss_pct": 0
        },
        {
            "ts": 1782217528,
            "status": "UP",
            "latency_ms": 0.5,
            "packet_loss_pct": 0
        },
        {
            "ts": 1782217543,
            "status": "UP",
            "latency_ms": 0.5,
            "packet_loss_pct": 0
        },
        {
            "ts": 1782217558,
            "status": "UP",
            "latency_ms": 0.5,
            "packet_loss_pct": 0
        },
        {
            "ts": 1782217575,
            "status": "UP",
            "latency_ms": 0.5,
            "packet_loss_pct": 0
        },
        {
            "ts": 1782217588,
            "status": "UP",
            "latency_ms": 0.5,
            "packet_loss_pct": 0
        },
        {
            "ts": 1782217603,
            "status": "UP",
            "latency_ms": 0.5,
            "packet_loss_pct": 0
        },
        {
            "ts": 1782217618,
            "status": "UP",
            "latency_ms": 0.5,
            "packet_loss_pct": 0
        },
        {
            "ts": 1782217635,
            "status": "UP",
            "latency_ms": 0.5,
            "packet_loss_pct": 0
        },
        {
            "ts": 1782217648,
            "status": "UP",
            "latency_ms": 0.5,
            "packet_loss_pct": 0
        },
        {
            "ts": 1782217651,
            "status": "UP",
            "latency_ms": 0.5,
            "packet_loss_pct": 0
        },
        {
            "ts": 1782217656,
            "status": "UP",
            "latency_ms": 0.5,
            "packet_loss_pct": 0
        },
        {
            "ts": 1782217663,
            "status": "UP",
            "latency_ms": 0.5,
            "packet_loss_pct": 0
        },
        {
            "ts": 1782217666,
            "status": "UP",
            "latency_ms": 0.5,
            "packet_loss_pct": 0
        },
        {
            "ts": 1782217678,
            "status": "UP",
            "latency_ms": 0.5,
            "packet_loss_pct": 0
        },
        {
            "ts": 1782217682,
            "status": "UP",
            "latency_ms": 0.5,
            "packet_loss_pct": 0
        },
        {
            "ts": 1782217692,
            "status": "UP",
            "latency_ms": 0.5,
            "packet_loss_pct": 0
        },
        {
            "ts": 1782217708,
            "status": "UP",
            "latency_ms": 0.5,
            "packet_loss_pct": 0
        },
        {
            "ts": 1782217712,
            "status": "UP",
            "latency_ms": 0.5,
            "packet_loss_pct": 0
        },
        {
            "ts": 1782217722,
            "status": "UP",
            "latency_ms": 0.5,
            "packet_loss_pct": 0
        },
        {
            "ts": 1782217732,
            "status": "UP",
            "latency_ms": 0.5,
            "packet_loss_pct": 0
        },
        {
            "ts": 1782217742,
            "status": "UP",
            "latency_ms": 0.5,
            "packet_loss_pct": 0
        },
        {
            "ts": 1782217752,
            "status": "UP",
            "latency_ms": 0.5,
            "packet_loss_pct": 0
        },
        {
            "ts": 1782217762,
            "status": "UP",
            "latency_ms": 0.5,
            "packet_loss_pct": 0
        },
        {
            "ts": 1782217772,
            "status": "UP",
            "latency_ms": 0.5,
            "packet_loss_pct": 0
        },
        {
            "ts": 1782217780,
            "status": "UP",
            "latency_ms": 0.5,
            "packet_loss_pct": 0
        },
        {
            "ts": 1782217795,
            "status": "UP",
            "latency_ms": 0.5,
            "packet_loss_pct": 0
        },
        {
            "ts": 1782324414,
            "status": "UP",
            "latency_ms": 0.5,
            "packet_loss_pct": 0
        },
        {
            "ts": 1782476336,
            "status": "UP",
            "latency_ms": 0.5,
            "packet_loss_pct": 0
        },
        {
            "ts": 1782476343,
            "status": "UP",
            "latency_ms": 0.5,
            "packet_loss_pct": 0
        },
        {
            "ts": 1782476353,
            "status": "UP",
            "latency_ms": 0.5,
            "packet_loss_pct": 0
        },
        {
            "ts": 1782479141,
            "status": "UP",
            "latency_ms": 0.5,
            "packet_loss_pct": 0
        },
        {
            "ts": 1782690082,
            "status": "DOWN",
            "latency_ms": null,
            "packet_loss_pct": 100
        },
        {
            "ts": 1782691044,
            "status": "UP",
            "latency_ms": 0.5,
            "packet_loss_pct": 0
        },
        {
            "ts": 1782691054,
            "status": "UP",
            "latency_ms": 0.5,
            "packet_loss_pct": 0
        },
        {
            "ts": 1782691118,
            "status": "UP",
            "latency_ms": 0.5,
            "packet_loss_pct": 0
        },
        {
            "ts": 1782691128,
            "status": "UP",
            "latency_ms": 0.5,
            "packet_loss_pct": 0
        },
        {
            "ts": 1782691153,
            "status": "UP",
            "latency_ms": 0.5,
            "packet_loss_pct": 0
        },
        {
            "ts": 1782691163,
            "status": "UP",
            "latency_ms": 0.5,
            "packet_loss_pct": 0
        },
        {
            "ts": 1782691173,
            "status": "UP",
            "latency_ms": 0.5,
            "packet_loss_pct": 0
        },
        {
            "ts": 1782691193,
            "status": "UP",
            "latency_ms": 0.5,
            "packet_loss_pct": 0
        },
        {
            "ts": 1782691219,
            "status": "UP",
            "latency_ms": 0.5,
            "packet_loss_pct": 0
        },
        {
            "ts": 1782691254,
            "status": "UP",
            "latency_ms": 0.5,
            "packet_loss_pct": 0
        },
        {
            "ts": 1782691515,
            "status": "UP",
            "latency_ms": 0.5,
            "packet_loss_pct": 0
        },
        {
            "ts": 1782691525,
            "status": "UP",
            "latency_ms": 0.5,
            "packet_loss_pct": 0
        },
        {
            "ts": 1782691548,
            "status": "UP",
            "latency_ms": 0.5,
            "packet_loss_pct": 0
        },
        {
            "ts": 1782691558,
            "status": "UP",
            "latency_ms": 0.5,
            "packet_loss_pct": 0
        },
        {
            "ts": 1782691579,
            "status": "UP",
            "latency_ms": 0.5,
            "packet_loss_pct": 0
        },
        {
            "ts": 1782691680,
            "status": "UP",
            "latency_ms": 0.5,
            "packet_loss_pct": 0
        },
        {
            "ts": 1782692961,
            "status": "UP",
            "latency_ms": 0.5,
            "packet_loss_pct": 0
        }
    ],
    "dc2932fbde8bcf3f": [
        {
            "ts": 1782136397,
            "status": "DOWN",
            "latency_ms": null,
            "packet_loss_pct": 100
        },
        {
            "ts": 1782136408,
            "status": "DOWN",
            "latency_ms": null,
            "packet_loss_pct": 100
        },
        {
            "ts": 1782136418,
            "status": "DOWN",
            "latency_ms": null,
            "packet_loss_pct": 100
        },
        {
            "ts": 1782136428,
            "status": "DOWN",
            "latency_ms": null,
            "packet_loss_pct": 100
        },
        {
            "ts": 1782136438,
            "status": "DOWN",
            "latency_ms": null,
            "packet_loss_pct": 100
        },
        {
            "ts": 1782136448,
            "status": "DOWN",
            "latency_ms": null,
            "packet_loss_pct": 100
        },
        {
            "ts": 1782136458,
            "status": "DOWN",
            "latency_ms": null,
            "packet_loss_pct": 100
        },
        {
            "ts": 1782136468,
            "status": "DOWN",
            "latency_ms": null,
            "packet_loss_pct": 100
        },
        {
            "ts": 1782136478,
            "status": "DOWN",
            "latency_ms": null,
            "packet_loss_pct": 100
        },
        {
            "ts": 1782136488,
            "status": "DOWN",
            "latency_ms": null,
            "packet_loss_pct": 100
        },
        {
            "ts": 1782136498,
            "status": "DOWN",
            "latency_ms": null,
            "packet_loss_pct": 100
        },
        {
            "ts": 1782136507,
            "status": "DOWN",
            "latency_ms": null,
            "packet_loss_pct": 100
        },
        {
            "ts": 1782136522,
            "status": "DOWN",
            "latency_ms": null,
            "packet_loss_pct": 100
        },
        {
            "ts": 1782136530,
            "status": "DOWN",
            "latency_ms": null,
            "packet_loss_pct": 100
        },
        {
            "ts": 1782136538,
            "status": "DOWN",
            "latency_ms": null,
            "packet_loss_pct": 100
        },
        {
            "ts": 1782136546,
            "status": "DOWN",
            "latency_ms": null,
            "packet_loss_pct": 100
        },
        {
            "ts": 1782136554,
            "status": "DOWN",
            "latency_ms": null,
            "packet_loss_pct": 100
        },
        {
            "ts": 1782136562,
            "status": "DOWN",
            "latency_ms": null,
            "packet_loss_pct": 100
        },
        {
            "ts": 1782136570,
            "status": "DOWN",
            "latency_ms": null,
            "packet_loss_pct": 100
        },
        {
            "ts": 1782136578,
            "status": "DOWN",
            "latency_ms": null,
            "packet_loss_pct": 100
        },
        {
            "ts": 1782136677,
            "status": "DOWN",
            "latency_ms": null,
            "packet_loss_pct": 100
        },
        {
            "ts": 1782136707,
            "status": "DOWN",
            "latency_ms": null,
            "packet_loss_pct": 100
        },
        {
            "ts": 1782136737,
            "status": "DOWN",
            "latency_ms": null,
            "packet_loss_pct": 100
        },
        {
            "ts": 1782136747,
            "status": "DOWN",
            "latency_ms": null,
            "packet_loss_pct": 100
        },
        {
            "ts": 1782136765,
            "status": "DOWN",
            "latency_ms": null,
            "packet_loss_pct": 100
        },
        {
            "ts": 1782136781,
            "status": "DOWN",
            "latency_ms": null,
            "packet_loss_pct": 100
        },
        {
            "ts": 1782136796,
            "status": "DOWN",
            "latency_ms": null,
            "packet_loss_pct": 100
        },
        {
            "ts": 1782136814,
            "status": "DOWN",
            "latency_ms": null,
            "packet_loss_pct": 100
        },
        {
            "ts": 1782136824,
            "status": "DOWN",
            "latency_ms": null,
            "packet_loss_pct": 100
        },
        {
            "ts": 1782136834,
            "status": "DOWN",
            "latency_ms": null,
            "packet_loss_pct": 100
        },
        {
            "ts": 1782136843,
            "status": "DOWN",
            "latency_ms": null,
            "packet_loss_pct": 100
        },
        {
            "ts": 1782136854,
            "status": "DOWN",
            "latency_ms": null,
            "packet_loss_pct": 100
        }
    ],
    "ae1f3b15d7c50341": [
        {
            "ts": 1782137048,
            "status": "DOWN",
            "latency_ms": null,
            "packet_loss_pct": 100
        },
        {
            "ts": 1782137056,
            "status": "DOWN",
            "latency_ms": null,
            "packet_loss_pct": 100
        },
        {
            "ts": 1782137064,
            "status": "DOWN",
            "latency_ms": null,
            "packet_loss_pct": 100
        },
        {
            "ts": 1782137072,
            "status": "DOWN",
            "latency_ms": null,
            "packet_loss_pct": 100
        },
        {
            "ts": 1782137080,
            "status": "DOWN",
            "latency_ms": null,
            "packet_loss_pct": 100
        },
        {
            "ts": 1782137089,
            "status": "DOWN",
            "latency_ms": null,
            "packet_loss_pct": 100
        },
        {
            "ts": 1782137105,
            "status": "DOWN",
            "latency_ms": null,
            "packet_loss_pct": 100
        },
        {
            "ts": 1782137121,
            "status": "DOWN",
            "latency_ms": null,
            "packet_loss_pct": 100
        },
        {
            "ts": 1782137136,
            "status": "DOWN",
            "latency_ms": null,
            "packet_loss_pct": 100
        },
        {
            "ts": 1782137153,
            "status": "DOWN",
            "latency_ms": null,
            "packet_loss_pct": 100
        },
        {
            "ts": 1782137170,
            "status": "DOWN",
            "latency_ms": null,
            "packet_loss_pct": 100
        },
        {
            "ts": 1782137185,
            "status": "DOWN",
            "latency_ms": null,
            "packet_loss_pct": 100
        },
        {
            "ts": 1782137202,
            "status": "DOWN",
            "latency_ms": null,
            "packet_loss_pct": 100
        },
        {
            "ts": 1782137234,
            "status": "DOWN",
            "latency_ms": null,
            "packet_loss_pct": 100
        },
        {
            "ts": 1782137249,
            "status": "DOWN",
            "latency_ms": null,
            "packet_loss_pct": 100
        },
        {
            "ts": 1782137280,
            "status": "DOWN",
            "latency_ms": null,
            "packet_loss_pct": 100
        },
        {
            "ts": 1782137297,
            "status": "DOWN",
            "latency_ms": null,
            "packet_loss_pct": 100
        },
        {
            "ts": 1782137314,
            "status": "DOWN",
            "latency_ms": null,
            "packet_loss_pct": 100
        },
        {
            "ts": 1782137329,
            "status": "DOWN",
            "latency_ms": null,
            "packet_loss_pct": 100
        },
        {
            "ts": 1782137346,
            "status": "DOWN",
            "latency_ms": null,
            "packet_loss_pct": 100
        },
        {
            "ts": 1782137361,
            "status": "DOWN",
            "latency_ms": null,
            "packet_loss_pct": 100
        },
        {
            "ts": 1782137405,
            "status": "DOWN",
            "latency_ms": null,
            "packet_loss_pct": 100
        },
        {
            "ts": 1782137416,
            "status": "DOWN",
            "latency_ms": null,
            "packet_loss_pct": 100
        },
        {
            "ts": 1782137435,
            "status": "DOWN",
            "latency_ms": null,
            "packet_loss_pct": 100
        },
        {
            "ts": 1782137450,
            "status": "DOWN",
            "latency_ms": null,
            "packet_loss_pct": 100
        },
        {
            "ts": 1782137473,
            "status": "DOWN",
            "latency_ms": null,
            "packet_loss_pct": 100
        },
        {
            "ts": 1782137490,
            "status": "DOWN",
            "latency_ms": null,
            "packet_loss_pct": 100
        },
        {
            "ts": 1782137506,
            "status": "DOWN",
            "latency_ms": null,
            "packet_loss_pct": 100
        },
        {
            "ts": 1782137521,
            "status": "DOWN",
            "latency_ms": null,
            "packet_loss_pct": 100
        },
        {
            "ts": 1782137530,
            "status": "DOWN",
            "latency_ms": null,
            "packet_loss_pct": 100
        },
        {
            "ts": 1782137537,
            "status": "DOWN",
            "latency_ms": null,
            "packet_loss_pct": 100
        },
        {
            "ts": 1782137545,
            "status": "DOWN",
            "latency_ms": null,
            "packet_loss_pct": 100
        },
        {
            "ts": 1782137553,
            "status": "DOWN",
            "latency_ms": null,
            "packet_loss_pct": 100
        },
        {
            "ts": 1782137608,
            "status": "DOWN",
            "latency_ms": null,
            "packet_loss_pct": 100
        },
        {
            "ts": 1782137626,
            "status": "DOWN",
            "latency_ms": null,
            "packet_loss_pct": 100
        },
        {
            "ts": 1782137641,
            "status": "DOWN",
            "latency_ms": null,
            "packet_loss_pct": 100
        },
        {
            "ts": 1782137658,
            "status": "DOWN",
            "latency_ms": null,
            "packet_loss_pct": 100
        },
        {
            "ts": 1782137673,
            "status": "DOWN",
            "latency_ms": null,
            "packet_loss_pct": 100
        },
        {
            "ts": 1782137699,
            "status": "DOWN",
            "latency_ms": null,
            "packet_loss_pct": 100
        },
        {
            "ts": 1782137713,
            "status": "DOWN",
            "latency_ms": null,
            "packet_loss_pct": 100
        },
        {
            "ts": 1782137721,
            "status": "DOWN",
            "latency_ms": null,
            "packet_loss_pct": 100
        },
        {
            "ts": 1782137729,
            "status": "DOWN",
            "latency_ms": null,
            "packet_loss_pct": 100
        },
        {
            "ts": 1782137737,
            "status": "DOWN",
            "latency_ms": null,
            "packet_loss_pct": 100
        },
        {
            "ts": 1782137745,
            "status": "DOWN",
            "latency_ms": null,
            "packet_loss_pct": 100
        },
        {
            "ts": 1782137764,
            "status": "DOWN",
            "latency_ms": null,
            "packet_loss_pct": 100
        },
        {
            "ts": 1782137778,
            "status": "DOWN",
            "latency_ms": null,
            "packet_loss_pct": 100
        },
        {
            "ts": 1782137801,
            "status": "DOWN",
            "latency_ms": null,
            "packet_loss_pct": 100
        },
        {
            "ts": 1782137809,
            "status": "DOWN",
            "latency_ms": null,
            "packet_loss_pct": 100
        },
        {
            "ts": 1782137817,
            "status": "DOWN",
            "latency_ms": null,
            "packet_loss_pct": 100
        },
        {
            "ts": 1782137825,
            "status": "DOWN",
            "latency_ms": null,
            "packet_loss_pct": 100
        },
        {
            "ts": 1782137833,
            "status": "DOWN",
            "latency_ms": null,
            "packet_loss_pct": 100
        },
        {
            "ts": 1782137841,
            "status": "DOWN",
            "latency_ms": null,
            "packet_loss_pct": 100
        },
        {
            "ts": 1782137849,
            "status": "DOWN",
            "latency_ms": null,
            "packet_loss_pct": 100
        },
        {
            "ts": 1782137865,
            "status": "DOWN",
            "latency_ms": null,
            "packet_loss_pct": 100
        },
        {
            "ts": 1782137880,
            "status": "DOWN",
            "latency_ms": null,
            "packet_loss_pct": 100
        },
        {
            "ts": 1782137888,
            "status": "DOWN",
            "latency_ms": null,
            "packet_loss_pct": 100
        },
        {
            "ts": 1782137895,
            "status": "DOWN",
            "latency_ms": null,
            "packet_loss_pct": 100
        },
        {
            "ts": 1782137905,
            "status": "DOWN",
            "latency_ms": null,
            "packet_loss_pct": 100
        },
        {
            "ts": 1782137915,
            "status": "DOWN",
            "latency_ms": null,
            "packet_loss_pct": 100
        },
        {
            "ts": 1782137925,
            "status": "DOWN",
            "latency_ms": null,
            "packet_loss_pct": 100
        }
    ],
    "f83b7bf25e6b5254": [
        {
            "ts": 1782216838,
            "status": "UP",
            "latency_ms": 0.5,
            "packet_loss_pct": 0
        },
        {
            "ts": 1782216855,
            "status": "UP",
            "latency_ms": 0.5,
            "packet_loss_pct": 0
        },
        {
            "ts": 1782216868,
            "status": "UP",
            "latency_ms": 0.5,
            "packet_loss_pct": 0
        },
        {
            "ts": 1782216883,
            "status": "UP",
            "latency_ms": 0.5,
            "packet_loss_pct": 0
        },
        {
            "ts": 1782216898,
            "status": "UP",
            "latency_ms": 0.5,
            "packet_loss_pct": 0
        },
        {
            "ts": 1782216915,
            "status": "UP",
            "latency_ms": 0.5,
            "packet_loss_pct": 0
        },
        {
            "ts": 1782216928,
            "status": "UP",
            "latency_ms": 0.5,
            "packet_loss_pct": 0
        },
        {
            "ts": 1782216943,
            "status": "UP",
            "latency_ms": 0.5,
            "packet_loss_pct": 0
        },
        {
            "ts": 1782216958,
            "status": "UP",
            "latency_ms": 0.5,
            "packet_loss_pct": 0
        },
        {
            "ts": 1782216975,
            "status": "UP",
            "latency_ms": 0.5,
            "packet_loss_pct": 0
        },
        {
            "ts": 1782216988,
            "status": "UP",
            "latency_ms": 0.5,
            "packet_loss_pct": 0
        },
        {
            "ts": 1782217003,
            "status": "UP",
            "latency_ms": 0.5,
            "packet_loss_pct": 0
        },
        {
            "ts": 1782217018,
            "status": "UP",
            "latency_ms": 0.5,
            "packet_loss_pct": 0
        },
        {
            "ts": 1782217035,
            "status": "UP",
            "latency_ms": 0.5,
            "packet_loss_pct": 0
        },
        {
            "ts": 1782217048,
            "status": "UP",
            "latency_ms": 0.5,
            "packet_loss_pct": 0
        },
        {
            "ts": 1782217063,
            "status": "UP",
            "latency_ms": 0.5,
            "packet_loss_pct": 0
        },
        {
            "ts": 1782217078,
            "status": "UP",
            "latency_ms": 0.5,
            "packet_loss_pct": 0
        },
        {
            "ts": 1782217095,
            "status": "UP",
            "latency_ms": 0.5,
            "packet_loss_pct": 0
        },
        {
            "ts": 1782217108,
            "status": "UP",
            "latency_ms": 0.5,
            "packet_loss_pct": 0
        },
        {
            "ts": 1782217123,
            "status": "UP",
            "latency_ms": 0.5,
            "packet_loss_pct": 0
        },
        {
            "ts": 1782217138,
            "status": "UP",
            "latency_ms": 0.5,
            "packet_loss_pct": 0
        },
        {
            "ts": 1782217155,
            "status": "UP",
            "latency_ms": 0.5,
            "packet_loss_pct": 0
        },
        {
            "ts": 1782217168,
            "status": "UP",
            "latency_ms": 0.5,
            "packet_loss_pct": 0
        },
        {
            "ts": 1782217183,
            "status": "UP",
            "latency_ms": 0.5,
            "packet_loss_pct": 0
        },
        {
            "ts": 1782217198,
            "status": "UP",
            "latency_ms": 0.5,
            "packet_loss_pct": 0
        },
        {
            "ts": 1782217215,
            "status": "UP",
            "latency_ms": 0.5,
            "packet_loss_pct": 0
        },
        {
            "ts": 1782217228,
            "status": "UP",
            "latency_ms": 0.5,
            "packet_loss_pct": 0
        },
        {
            "ts": 1782217243,
            "status": "UP",
            "latency_ms": 0.5,
            "packet_loss_pct": 0
        },
        {
            "ts": 1782217258,
            "status": "UP",
            "latency_ms": 0.5,
            "packet_loss_pct": 0
        },
        {
            "ts": 1782217275,
            "status": "UP",
            "latency_ms": 0.5,
            "packet_loss_pct": 0
        },
        {
            "ts": 1782217290,
            "status": "UP",
            "latency_ms": 0.5,
            "packet_loss_pct": 0
        },
        {
            "ts": 1782217305,
            "status": "UP",
            "latency_ms": 0.5,
            "packet_loss_pct": 0
        },
        {
            "ts": 1782217321,
            "status": "UP",
            "latency_ms": 0.5,
            "packet_loss_pct": 0
        },
        {
            "ts": 1782217335,
            "status": "UP",
            "latency_ms": 0.5,
            "packet_loss_pct": 0
        },
        {
            "ts": 1782217348,
            "status": "UP",
            "latency_ms": 0.5,
            "packet_loss_pct": 0
        },
        {
            "ts": 1782217364,
            "status": "UP",
            "latency_ms": 0.5,
            "packet_loss_pct": 0
        },
        {
            "ts": 1782217379,
            "status": "UP",
            "latency_ms": 0.5,
            "packet_loss_pct": 0
        },
        {
            "ts": 1782217395,
            "status": "UP",
            "latency_ms": 0.5,
            "packet_loss_pct": 0
        },
        {
            "ts": 1782217409,
            "status": "UP",
            "latency_ms": 0.5,
            "packet_loss_pct": 0
        },
        {
            "ts": 1782217424,
            "status": "UP",
            "latency_ms": 0.5,
            "packet_loss_pct": 0
        },
        {
            "ts": 1782217439,
            "status": "UP",
            "latency_ms": 0.5,
            "packet_loss_pct": 0
        },
        {
            "ts": 1782217455,
            "status": "UP",
            "latency_ms": 0.5,
            "packet_loss_pct": 0
        },
        {
            "ts": 1782217468,
            "status": "UP",
            "latency_ms": 0.5,
            "packet_loss_pct": 0
        },
        {
            "ts": 1782217484,
            "status": "UP",
            "latency_ms": 0.5,
            "packet_loss_pct": 0
        },
        {
            "ts": 1782217498,
            "status": "UP",
            "latency_ms": 0.5,
            "packet_loss_pct": 0
        },
        {
            "ts": 1782217504,
            "status": "UP",
            "latency_ms": 0.5,
            "packet_loss_pct": 0
        },
        {
            "ts": 1782217515,
            "status": "UP",
            "latency_ms": 0.5,
            "packet_loss_pct": 0
        },
        {
            "ts": 1782217528,
            "status": "UP",
            "latency_ms": 0.5,
            "packet_loss_pct": 0
        },
        {
            "ts": 1782217543,
            "status": "UP",
            "latency_ms": 0.5,
            "packet_loss_pct": 0
        },
        {
            "ts": 1782217558,
            "status": "UP",
            "latency_ms": 0.5,
            "packet_loss_pct": 0
        },
        {
            "ts": 1782217575,
            "status": "UP",
            "latency_ms": 0.5,
            "packet_loss_pct": 0
        },
        {
            "ts": 1782217588,
            "status": "UP",
            "latency_ms": 0.5,
            "packet_loss_pct": 0
        },
        {
            "ts": 1782217603,
            "status": "UP",
            "latency_ms": 0.5,
            "packet_loss_pct": 0
        },
        {
            "ts": 1782217618,
            "status": "UP",
            "latency_ms": 0.5,
            "packet_loss_pct": 0
        },
        {
            "ts": 1782217635,
            "status": "UP",
            "latency_ms": 0.5,
            "packet_loss_pct": 0
        },
        {
            "ts": 1782217648,
            "status": "UP",
            "latency_ms": 0.5,
            "packet_loss_pct": 0
        },
        {
            "ts": 1782217651,
            "status": "UP",
            "latency_ms": 0.5,
            "packet_loss_pct": 0
        },
        {
            "ts": 1782217656,
            "status": "UP",
            "latency_ms": 0.5,
            "packet_loss_pct": 0
        },
        {
            "ts": 1782217663,
            "status": "UP",
            "latency_ms": 0.5,
            "packet_loss_pct": 0
        },
        {
            "ts": 1782217666,
            "status": "UP",
            "latency_ms": 0.5,
            "packet_loss_pct": 0
        }
    ],
    "9d598cafcc450b05": [
        {
            "ts": 1783554683,
            "status": "UP",
            "latency_ms": 0.5,
            "packet_loss_pct": 0
        },
        {
            "ts": 1783554742,
            "status": "UP",
            "latency_ms": 0.5,
            "packet_loss_pct": 0
        },
        {
            "ts": 1783554802,
            "status": "UP",
            "latency_ms": 0.5,
            "packet_loss_pct": 0
        },
        {
            "ts": 1783554862,
            "status": "UP",
            "latency_ms": 0.5,
            "packet_loss_pct": 0
        },
        {
            "ts": 1783554922,
            "status": "UP",
            "latency_ms": 0.5,
            "packet_loss_pct": 0
        },
        {
            "ts": 1783554982,
            "status": "UP",
            "latency_ms": 0.5,
            "packet_loss_pct": 0
        },
        {
            "ts": 1783555042,
            "status": "UP",
            "latency_ms": 0.5,
            "packet_loss_pct": 0
        },
        {
            "ts": 1783555102,
            "status": "UP",
            "latency_ms": 0.5,
            "packet_loss_pct": 0
        },
        {
            "ts": 1783555162,
            "status": "UP",
            "latency_ms": 0.5,
            "packet_loss_pct": 0
        },
        {
            "ts": 1783555222,
            "status": "UP",
            "latency_ms": 0.5,
            "packet_loss_pct": 0
        },
        {
            "ts": 1783555282,
            "status": "UP",
            "latency_ms": 0.5,
            "packet_loss_pct": 0
        },
        {
            "ts": 1783555342,
            "status": "UP",
            "latency_ms": 0.5,
            "packet_loss_pct": 0
        },
        {
            "ts": 1783555402,
            "status": "UP",
            "latency_ms": 0.5,
            "packet_loss_pct": 0
        },
        {
            "ts": 1783555462,
            "status": "UP",
            "latency_ms": 0.5,
            "packet_loss_pct": 0
        },
        {
            "ts": 1783555522,
            "status": "UP",
            "latency_ms": 0.5,
            "packet_loss_pct": 0
        },
        {
            "ts": 1783555582,
            "status": "UP",
            "latency_ms": 0.5,
            "packet_loss_pct": 0
        },
        {
            "ts": 1783555642,
            "status": "UP",
            "latency_ms": 0.5,
            "packet_loss_pct": 0
        },
        {
            "ts": 1783555702,
            "status": "UP",
            "latency_ms": 0.5,
            "packet_loss_pct": 0
        },
        {
            "ts": 1783555762,
            "status": "UP",
            "latency_ms": 0.5,
            "packet_loss_pct": 0
        },
        {
            "ts": 1783555822,
            "status": "UP",
            "latency_ms": 0.5,
            "packet_loss_pct": 0
        },
        {
            "ts": 1783555882,
            "status": "UP",
            "latency_ms": 0.5,
            "packet_loss_pct": 0
        },
        {
            "ts": 1783555942,
            "status": "UP",
            "latency_ms": 0.5,
            "packet_loss_pct": 0
        },
        {
            "ts": 1783556010,
            "status": "UP",
            "latency_ms": 0.5,
            "packet_loss_pct": 0
        },
        {
            "ts": 1783556062,
            "status": "UP",
            "latency_ms": 0.5,
            "packet_loss_pct": 0
        },
        {
            "ts": 1783556122,
            "status": "UP",
            "latency_ms": 0.5,
            "packet_loss_pct": 0
        },
        {
            "ts": 1783556182,
            "status": "UP",
            "latency_ms": 0.5,
            "packet_loss_pct": 0
        },
        {
            "ts": 1783556242,
            "status": "UP",
            "latency_ms": 0.5,
            "packet_loss_pct": 0
        },
        {
            "ts": 1783556302,
            "status": "UP",
            "latency_ms": 0.5,
            "packet_loss_pct": 0
        },
        {
            "ts": 1783556362,
            "status": "UP",
            "latency_ms": 0.5,
            "packet_loss_pct": 0
        },
        {
            "ts": 1783556422,
            "status": "UP",
            "latency_ms": 0.5,
            "packet_loss_pct": 0
        },
        {
            "ts": 1783556482,
            "status": "UP",
            "latency_ms": 0.5,
            "packet_loss_pct": 0
        },
        {
            "ts": 1783556542,
            "status": "UP",
            "latency_ms": 0.5,
            "packet_loss_pct": 0
        },
        {
            "ts": 1783556602,
            "status": "UP",
            "latency_ms": 0.5,
            "packet_loss_pct": 0
        },
        {
            "ts": 1783556662,
            "status": "UP",
            "latency_ms": 0.5,
            "packet_loss_pct": 0
        },
        {
            "ts": 1783556722,
            "status": "UP",
            "latency_ms": 0.5,
            "packet_loss_pct": 0
        },
        {
            "ts": 1783556782,
            "status": "UP",
            "latency_ms": 0.5,
            "packet_loss_pct": 0
        },
        {
            "ts": 1783556842,
            "status": "UP",
            "latency_ms": 0.5,
            "packet_loss_pct": 0
        },
        {
            "ts": 1783556902,
            "status": "UP",
            "latency_ms": 0.5,
            "packet_loss_pct": 0
        },
        {
            "ts": 1783556962,
            "status": "UP",
            "latency_ms": 0.5,
            "packet_loss_pct": 0
        },
        {
            "ts": 1783557022,
            "status": "UP",
            "latency_ms": 0.5,
            "packet_loss_pct": 0
        },
        {
            "ts": 1783557082,
            "status": "UP",
            "latency_ms": 0.5,
            "packet_loss_pct": 0
        },
        {
            "ts": 1783557142,
            "status": "UP",
            "latency_ms": 0.5,
            "packet_loss_pct": 0
        },
        {
            "ts": 1783557202,
            "status": "UP",
            "latency_ms": 0.5,
            "packet_loss_pct": 0
        },
        {
            "ts": 1783557262,
            "status": "UP",
            "latency_ms": 0.5,
            "packet_loss_pct": 0
        },
        {
            "ts": 1783557322,
            "status": "UP",
            "latency_ms": 0.5,
            "packet_loss_pct": 0
        },
        {
            "ts": 1783557382,
            "status": "UP",
            "latency_ms": 0.5,
            "packet_loss_pct": 0
        },
        {
            "ts": 1783557450,
            "status": "UP",
            "latency_ms": 0.5,
            "packet_loss_pct": 0
        },
        {
            "ts": 1783557502,
            "status": "UP",
            "latency_ms": 0.5,
            "packet_loss_pct": 0
        },
        {
            "ts": 1783557562,
            "status": "UP",
            "latency_ms": 0.5,
            "packet_loss_pct": 0
        },
        {
            "ts": 1783557622,
            "status": "UP",
            "latency_ms": 0.5,
            "packet_loss_pct": 0
        },
        {
            "ts": 1783557682,
            "status": "UP",
            "latency_ms": 0.5,
            "packet_loss_pct": 0
        },
        {
            "ts": 1783557742,
            "status": "UP",
            "latency_ms": 0.5,
            "packet_loss_pct": 0
        },
        {
            "ts": 1783557802,
            "status": "UP",
            "latency_ms": 0.5,
            "packet_loss_pct": 0
        },
        {
            "ts": 1783557862,
            "status": "UP",
            "latency_ms": 0.5,
            "packet_loss_pct": 0
        },
        {
            "ts": 1783557922,
            "status": "UP",
            "latency_ms": 0.5,
            "packet_loss_pct": 0
        },
        {
            "ts": 1783557982,
            "status": "UP",
            "latency_ms": 0.5,
            "packet_loss_pct": 0
        },
        {
            "ts": 1783558042,
            "status": "UP",
            "latency_ms": 0.5,
            "packet_loss_pct": 0
        },
        {
            "ts": 1783558103,
            "status": "UP",
            "latency_ms": 0.5,
            "packet_loss_pct": 0
        },
        {
            "ts": 1783560774,
            "status": "UP",
            "latency_ms": 0.5,
            "packet_loss_pct": 0
        },
        {
            "ts": 1783560788,
            "status": "UP",
            "latency_ms": 0.5,
            "packet_loss_pct": 0
        }
    ],
    "b71d4c3853fa1f3d": [
        {
            "ts": 1782285677,
            "status": "DOWN",
            "latency_ms": null,
            "packet_loss_pct": 100
        },
        {
            "ts": 1782285737,
            "status": "DOWN",
            "latency_ms": null,
            "packet_loss_pct": 100
        },
        {
            "ts": 1782285797,
            "status": "DOWN",
            "latency_ms": null,
            "packet_loss_pct": 100
        },
        {
            "ts": 1782285857,
            "status": "DOWN",
            "latency_ms": null,
            "packet_loss_pct": 100
        },
        {
            "ts": 1782285917,
            "status": "DOWN",
            "latency_ms": null,
            "packet_loss_pct": 100
        },
        {
            "ts": 1782285977,
            "status": "DOWN",
            "latency_ms": null,
            "packet_loss_pct": 100
        },
        {
            "ts": 1782286037,
            "status": "DOWN",
            "latency_ms": null,
            "packet_loss_pct": 100
        },
        {
            "ts": 1782286097,
            "status": "DOWN",
            "latency_ms": null,
            "packet_loss_pct": 100
        },
        {
            "ts": 1782286157,
            "status": "DOWN",
            "latency_ms": null,
            "packet_loss_pct": 100
        },
        {
            "ts": 1782286217,
            "status": "DOWN",
            "latency_ms": null,
            "packet_loss_pct": 100
        },
        {
            "ts": 1782286234,
            "status": "DOWN",
            "latency_ms": null,
            "packet_loss_pct": 100
        },
        {
            "ts": 1782286243,
            "status": "DOWN",
            "latency_ms": null,
            "packet_loss_pct": 100
        },
        {
            "ts": 1782286258,
            "status": "DOWN",
            "latency_ms": null,
            "packet_loss_pct": 100
        },
        {
            "ts": 1782286282,
            "status": "DOWN",
            "latency_ms": null,
            "packet_loss_pct": 100
        },
        {
            "ts": 1782286303,
            "status": "DOWN",
            "latency_ms": null,
            "packet_loss_pct": 100
        },
        {
            "ts": 1782286318,
            "status": "DOWN",
            "latency_ms": null,
            "packet_loss_pct": 100
        },
        {
            "ts": 1782286342,
            "status": "DOWN",
            "latency_ms": null,
            "packet_loss_pct": 100
        },
        {
            "ts": 1782286364,
            "status": "DOWN",
            "latency_ms": null,
            "packet_loss_pct": 100
        },
        {
            "ts": 1782286379,
            "status": "DOWN",
            "latency_ms": null,
            "packet_loss_pct": 100
        },
        {
            "ts": 1782286402,
            "status": "DOWN",
            "latency_ms": null,
            "packet_loss_pct": 100
        },
        {
            "ts": 1782286457,
            "status": "DOWN",
            "latency_ms": null,
            "packet_loss_pct": 100
        },
        {
            "ts": 1782286517,
            "status": "DOWN",
            "latency_ms": null,
            "packet_loss_pct": 100
        },
        {
            "ts": 1782286577,
            "status": "DOWN",
            "latency_ms": null,
            "packet_loss_pct": 100
        },
        {
            "ts": 1782286637,
            "status": "DOWN",
            "latency_ms": null,
            "packet_loss_pct": 100
        },
        {
            "ts": 1782286709,
            "status": "DOWN",
            "latency_ms": null,
            "packet_loss_pct": 100
        },
        {
            "ts": 1782288397,
            "status": "DOWN",
            "latency_ms": null,
            "packet_loss_pct": 100
        },
        {
            "ts": 1782288416,
            "status": "DOWN",
            "latency_ms": null,
            "packet_loss_pct": 100
        },
        {
            "ts": 1782288436,
            "status": "DOWN",
            "latency_ms": null,
            "packet_loss_pct": 100
        },
        {
            "ts": 1782288456,
            "status": "DOWN",
            "latency_ms": null,
            "packet_loss_pct": 100
        },
        {
            "ts": 1782288499,
            "status": "DOWN",
            "latency_ms": null,
            "packet_loss_pct": 100
        },
        {
            "ts": 1782288514,
            "status": "DOWN",
            "latency_ms": null,
            "packet_loss_pct": 100
        },
        {
            "ts": 1782299122,
            "status": "DOWN",
            "latency_ms": null,
            "packet_loss_pct": 100
        },
        {
            "ts": 1782300653,
            "status": "DOWN",
            "latency_ms": null,
            "packet_loss_pct": 100
        },
        {
            "ts": 1782301020,
            "status": "DOWN",
            "latency_ms": null,
            "packet_loss_pct": 100
        },
        {
            "ts": 1782305372,
            "status": "DOWN",
            "latency_ms": null,
            "packet_loss_pct": 100
        },
        {
            "ts": 1782305447,
            "status": "DOWN",
            "latency_ms": null,
            "packet_loss_pct": 100
        },
        {
            "ts": 1782305463,
            "status": "DOWN",
            "latency_ms": null,
            "packet_loss_pct": 100
        },
        {
            "ts": 1782305477,
            "status": "DOWN",
            "latency_ms": null,
            "packet_loss_pct": 100
        },
        {
            "ts": 1782305506,
            "status": "DOWN",
            "latency_ms": null,
            "packet_loss_pct": 100
        },
        {
            "ts": 1782305527,
            "status": "DOWN",
            "latency_ms": null,
            "packet_loss_pct": 100
        },
        {
            "ts": 1782305534,
            "status": "DOWN",
            "latency_ms": null,
            "packet_loss_pct": 100
        },
        {
            "ts": 1782305552,
            "status": "DOWN",
            "latency_ms": null,
            "packet_loss_pct": 100
        },
        {
            "ts": 1782305573,
            "status": "DOWN",
            "latency_ms": null,
            "packet_loss_pct": 100
        },
        {
            "ts": 1782308346,
            "status": "DOWN",
            "latency_ms": null,
            "packet_loss_pct": 100
        },
        {
            "ts": 1782308367,
            "status": "DOWN",
            "latency_ms": null,
            "packet_loss_pct": 100
        },
        {
            "ts": 1782308377,
            "status": "DOWN",
            "latency_ms": null,
            "packet_loss_pct": 100
        },
        {
            "ts": 1782308392,
            "status": "DOWN",
            "latency_ms": null,
            "packet_loss_pct": 100
        },
        {
            "ts": 1782308422,
            "status": "DOWN",
            "latency_ms": null,
            "packet_loss_pct": 100
        },
        {
            "ts": 1782308437,
            "status": "DOWN",
            "latency_ms": null,
            "packet_loss_pct": 100
        },
        {
            "ts": 1782308452,
            "status": "DOWN",
            "latency_ms": null,
            "packet_loss_pct": 100
        },
        {
            "ts": 1782308481,
            "status": "DOWN",
            "latency_ms": null,
            "packet_loss_pct": 100
        },
        {
            "ts": 1782309233,
            "status": "DOWN",
            "latency_ms": null,
            "packet_loss_pct": 100
        },
        {
            "ts": 1782309254,
            "status": "DOWN",
            "latency_ms": null,
            "packet_loss_pct": 100
        },
        {
            "ts": 1782309288,
            "status": "DOWN",
            "latency_ms": null,
            "packet_loss_pct": 100
        },
        {
            "ts": 1782324347,
            "status": "DOWN",
            "latency_ms": null,
            "packet_loss_pct": 100
        },
        {
            "ts": 1782324368,
            "status": "DOWN",
            "latency_ms": null,
            "packet_loss_pct": 100
        },
        {
            "ts": 1782324377,
            "status": "DOWN",
            "latency_ms": null,
            "packet_loss_pct": 100
        },
        {
            "ts": 1782324387,
            "status": "DOWN",
            "latency_ms": null,
            "packet_loss_pct": 100
        },
        {
            "ts": 1782324397,
            "status": "DOWN",
            "latency_ms": null,
            "packet_loss_pct": 100
        },
        {
            "ts": 1782324407,
            "status": "DOWN",
            "latency_ms": null,
            "packet_loss_pct": 100
        }
    ]
}